{
  "size": [20, 20],
  "pear_trees": {
    "tree_0_0": {
      "position": [1,5],
      "pears": 3
    },
    "tree_0_1": {
      "position": [1,10],
      "pears": 0
    },
    "tree_0_2": {
      "position": [1,15],
      "pears": 2
    },
    "tree_1_0": {
      "position": [5,5],
      "pears": 1
    },
    "tree_1_1": {
      "position": [5,10],
      "pears": 2
    },
    "tree_1_2": {
      "position": [5,15],
      "pears": 0
    }
  },
  "meteorological_data": {
    "humidity": 65,
    "temperature": 23,
    "light": "medium",
    "wind": "low"
  },
  "datetime": "2025-01-09T10:00:00"
}
